aiodukeenergy/__init__.py
aiodukeenergy/dukeenergy.py
aiodukeenergy/py.typed
aiodukeenergy-0.3.0.dist-info/LICENSE
aiodukeenergy-0.3.0.dist-info/METADATA
aiodukeenergy-0.3.0.dist-info/WHEEL
aiodukeenergy-0.3.0.dist-info/RECORD
