Metadata-Version: 2.3
Name: aiodukeenergy
Version: 0.3.0
Summary: Asyncio Duke Energy
License: MIT
Author: Jason Hunter
Author-email: hunterjm@gmail.com
Requires-Python: >=3.8,<4.0
Classifier: Development Status :: 2 - Pre-Alpha
Classifier: Intended Audience :: Developers
Classifier: License :: OSI Approved :: MIT License
Classifier: Natural Language :: English
Classifier: Operating System :: OS Independent
Classifier: Programming Language :: Python :: 3
Classifier: Programming Language :: Python :: 3.8
Classifier: Programming Language :: Python :: 3.9
Classifier: Programming Language :: Python :: 3.10
Classifier: Programming Language :: Python :: 3.11
Classifier: Programming Language :: Python :: 3.12
Classifier: Programming Language :: Python :: 3.13
Classifier: Topic :: Software Development :: Libraries
Requires-Dist: aiohttp (>=3.9.0)
Requires-Dist: yarl (>=1.9.0)
Project-URL: Bug Tracker, https://github.com/hunterjm/aiodukeenergy/issues
Project-URL: Changelog, https://github.com/hunterjm/aiodukeenergy/blob/main/CHANGELOG.md
Project-URL: Documentation, https://aiodukeenergy.readthedocs.io
Project-URL: Repository, https://github.com/hunterjm/aiodukeenergy
